MANIFEST.in
README.md
release_notes.rst
setup.py
docs/Makefile
docs/conf.py
docs/index.rst
docs/make.bat
docs/namedspace.rst
docs/html/.buildinfo
docs/html/genindex.html
docs/html/index.html
docs/html/namedspace.html
docs/html/objects.inv
docs/html/py-modindex.html
docs/html/search.html
docs/html/searchindex.js
docs/html/_modules/index.html
docs/html/_modules/namedspace.html
docs/html/_sources/index.txt
docs/html/_sources/namedspace.txt
docs/html/_static/ajax-loader.gif
docs/html/_static/basic.css
docs/html/_static/comment-bright.png
docs/html/_static/comment-close.png
docs/html/_static/comment.png
docs/html/_static/default.css
docs/html/_static/doctools.js
docs/html/_static/down-pressed.png
docs/html/_static/down.png
docs/html/_static/file.png
docs/html/_static/jquery.js
docs/html/_static/minus.png
docs/html/_static/plus.png
docs/html/_static/pygments.css
docs/html/_static/searchtools.js
docs/html/_static/sidebar.js
docs/html/_static/underscore.js
docs/html/_static/up-pressed.png
docs/html/_static/up.png
docs/html/_static/websupport.js
namedspace/__init__.py
namedspace.egg-info/PKG-INFO
namedspace.egg-info/SOURCES.txt
namedspace.egg-info/dependency_links.txt
namedspace.egg-info/pbr.json
namedspace.egg-info/requires.txt
namedspace.egg-info/top_level.txt
tests/__init__.py
tests/test_namedspace_whitebox.py