Metadata-Version: 1.0
Name: namedspace
Version: 1.2.1
Summary: Namespace class factory.
Home-page: https://github.com/wsmith323/namedspace
Author: Warren A. Smith
Author-email: warren@wandrsmith.net
License: MIT
Keywords: namedspace namespace
Platform: UNKNOWN
